setup.py
games/__init__.py
games/number_guesser.py
games_mlnd_exercise.egg-info/PKG-INFO
games_mlnd_exercise.egg-info/SOURCES.txt
games_mlnd_exercise.egg-info/dependency_links.txt
games_mlnd_exercise.egg-info/not-zip-safe
games_mlnd_exercise.egg-info/top_level.txt