Metadata-Version: 1.0
Name: games-mlnd-exercise
Version: 0.1
Summary: A package containing list of games to play
Home-page: UNKNOWN
Author: UNKNOWN
Author-email: UNKNOWN
License: UNKNOWN
Platform: UNKNOWN
